src/__init__.py
src/cli.py
src/cli_test.py
src/piptree.py
src/tree.py
src/util.py
piptree2-0.1.1.dist-info/LICENSE
piptree2-0.1.1.dist-info/METADATA
piptree2-0.1.1.dist-info/WHEEL
piptree2-0.1.1.dist-info/entry_points.txt
piptree2-0.1.1.dist-info/top_level.txt
piptree2-0.1.1.dist-info/RECORD
